logorama
