Metadata-Version: 1.0
Name: logorama
Version: 0.0.2
Summary: Light weight colorful python logger
Home-page: https://github.com/kapilsh/logorama
Author: Kapil Sharma
Author-email: sharmakapil8@gmail.com
License: UNKNOWN
Platform: UNKNOWN
